py2log/__init__.py
py2log-0.1.0.dist-info/AUTHORS.md
py2log-0.1.0.dist-info/LICENSE
py2log-0.1.0.dist-info/METADATA
py2log-0.1.0.dist-info/WHEEL
py2log-0.1.0.dist-info/top_level.txt
py2log-0.1.0.dist-info/RECORD
