Metadata-Version: 2.1
Name: py2log
Version: 0.1.0
Summary: UNKNOWN
Home-page: UNKNOWN
License: UNKNOWN
Platform: UNKNOWN
Provides-Extra: colorlog
Requires-Dist: colorlog ; extra == 'colorlog'
